.gitignore
.readthedocs.yml
LICENSE
MANIFEST.in
README.md
conftest.py
pyproject.toml
requirements-dev.txt
requirements-parallel.txt
requirements.txt
setup.py
tasks.py
.github/workflows/test.yml
.github/workflows/twine_release.yml
docs/Makefile
docs/autosumm.rst
docs/conf.py
docs/index.rst
docs/make.bat
docs/requirements.txt
docs/api/sscutils.BaseEntity.rst
docs/api/sscutils.Col.rst
docs/api/sscutils.CompositeTypeBase.rst
docs/api/sscutils.IndexBase.rst
docs/api/sscutils.Nullable.rst
docs/api/sscutils.PipelineRegistry.rst
docs/api/sscutils.ScruTable.rst
docs/api/sscutils.TableFactory.rst
docs/api/sscutils.TableFeaturesBase.rst
docs/api/sscutils.create_trepo_with_subsets.rst
docs/api/sscutils.dump_dfs_to_tables.rst
docs/api/sscutils.dump_dfs_to_trepos.rst
docs/api/sscutils.run_step.rst
docs/notebooks/doc-000-intro.rst
docs/notebooks/doc-001-quickstart.rst
docs/notebooks/doc-002-conventions.rst
docs/notebooks/doc-003-mock-artifacts.rst
docs/notebooks/doc-004-glossary.rst
docs/notebooks/doc-005-rules.rst
docs/notebooks/doc-006-metadata.rst
docs/release_notes/main.rst
docs/release_notes/v0.0.0.rst
docs/release_notes/v0.0.1.rst
docs/release_notes/v0.0.2.rst
docs/release_notes/v0.0.3.rst
docs/release_notes/v0.1.0.rst
docs/release_notes/v0.1.1.rst
docs/release_notes/v0.2.0.rst
docs/release_notes/v0.2.1.rst
docs/release_notes/v0.2.2.rst
docs/release_notes/v0.2.3.rst
docs/release_notes/v0.2.4.rst
docs/release_notes/v0.2.5.rst
docs/release_notes/v0.2.7.rst
docs/release_notes/v0.3.0.rst
docs/release_notes/v0.3.1.rst
docs/release_notes/v0.3.2.rst
docs/release_notes/v0.3.3.rst
docs_config/conf.py
docs_config/current_release.rst
docs_config/requirements.txt
docs_config/release_notes/main.rst
docs_config/release_notes/v0.0.0.rst
docs_config/release_notes/v0.0.1.rst
docs_config/release_notes/v0.0.2.rst
docs_config/release_notes/v0.0.3.rst
docs_config/release_notes/v0.1.0.rst
docs_config/release_notes/v0.1.1.rst
docs_config/release_notes/v0.2.0.rst
sscutils.egg-info/PKG-INFO
sscutils.egg-info/SOURCES.txt
sscutils.egg-info/dependency_links.txt
sscutils.egg-info/requires.txt
sscutils.egg-info/top_level.txt
