Metadata-Version: 2.1
Name: sscutils
Version: 0.3.3
Summary: sscu-budapest utilities for scientific data engineering
Home-page: https://github.com/sscu-budapest/sscutils
Author: Social Science Computing Unit Budapest
License: MIT
Platform: any
Classifier: License :: OSI Approved :: MIT License
Requires-Python: >=3.8
Provides-Extra: parallel
Provides-Extra: dev
Provides-Extra: complete
License-File: LICENSE
